alembic/README.md
alembic/env.py
alembic/script.py.mako
alembic/versions/2024_03_01_0537-99423c1dec60_create_tables.py
alembic/versions/2024_03_13_0518-82a0c686152d_add_title_error_code_mapping_and_errors_.py
alembic/versions/2024_03_22_0010-ffe2f57bd288_create_output_parameter.py
alembic/versions/2024_04_03_2257-4630ab8c198e_create_bitwarden_credential_parameter_.py
alembic/versions/2024_04_08_2347-ea8e24d0bc8e_add_orgs_max_retries_per_step.py
alembic/versions/2024_04_09_0058-8335d7fecef9_add_new_indices_to_tasks_table.py
alembic/versions/2024_04_23_2153-24303f1669a7_add_domain_to_organizations_table.py
alembic/versions/2024_04_28_2320-68d78072fdb5_add_org_task_step_index.py
alembic/versions/2024_05_05_0249-c4dca14a5e69_add_org_task_index_for_steps_table.py
alembic/versions/2024_05_11_2104-8792454ce498_add_max_steps_per_run_to_task.py
alembic/versions/2024_05_14_0114-bf561125112f_add_workflow_permanent_id_and_version_.py
alembic/versions/2024_05_14_0245-baec12642d77_add_workflow_permanent_id_constraint_.py
alembic/versions/2024_05_16_1729-04bf06540db6_add_proxy_location_and_webhook_callback_.py
alembic/versions/2024_06_07_2257-312d305c6b18_add_task_generations_table.py
alembic/versions/2024_06_11_0502-2c163e606a3d_add_collection_id_to_bitwarden_.py
alembic/versions/2024_06_27_1949-485667adef01_add_is_saved_task_to_workflows.py
alembic/versions/2024_07_09_1823-bea545cb21b4_add_workflow_permanent_id_and_.py
alembic/versions/2024_07_11_1644-ac679ea03578_create_bitwarden_identity_parameter_.py
alembic/versions/2024_07_12_0321-370cb81c73e7_add_totp_verification_url_to_tasks_.py
alembic/versions/2024_07_17_2227-94bc3829eed6_add_step_id_index_to_artifacts_table.py
alembic/versions/2024_07_31_0932-c5ed5a3a14eb_add_residential_ie_to_proxylocation_enum.py
alembic/versions/2024_08_06_1515-8f237f00faeb_add_gb_proxy.py
alembic/versions/2024_08_23_2012-6de11b2be7c8_add_suggested_title_to_task_generations_.py
skyvern-1.0.6.dist-info/METADATA
skyvern-1.0.6.dist-info/WHEEL
skyvern-1.0.6.dist-info/entry_points.txt
skyvern-1.0.6.dist-info/licenses/LICENSE
skyvern-1.0.6.dist-info/RECORD
