Metadata-Version: 2.4
Name: skyvern
Version: 1.0.6
Author-email: Skyvern AI <info@skyvern.com>
License-File: LICENSE
Requires-Python: <3.14,>=3.11
Requires-Dist: aioboto3<15,>=14.3.0
Requires-Dist: aiofiles<25,>=24.1.0
Requires-Dist: aiohttp<4,>=3.8.5
Requires-Dist: aioredlock<0.8,>=0.7.3
Requires-Dist: alembic<2,>=1.12.1
Requires-Dist: anthropic<0.51,>=0.50.0
Requires-Dist: asyncache<0.4,>=0.3.1
Requires-Dist: asyncpg<0.31,>=0.30.0
Requires-Dist: azure-identity<2,>=1.24.0
Requires-Dist: azure-keyvault-secrets<5,>=4.2.0
Requires-Dist: azure-storage-blob>=12.26.0
Requires-Dist: cachetools<6,>=5.3.2
Requires-Dist: curlparser<0.2,>=0.1.0
Requires-Dist: email-validator<3,>=2.2.0
Requires-Dist: fastapi<0.116,>=0.115.4
Requires-Dist: fastmcp<3,>=2.10.1
Requires-Dist: filetype<2,>=1.2.0
Requires-Dist: google-cloud-aiplatform<2,>=1.90.0
Requires-Dist: greenlet==3.0.3; python_version >= '3.11' and python_version < '3.12'
Requires-Dist: greenlet>3.0.3; python_version >= '3.12' and python_version < '3.14'
Requires-Dist: httpx[socks]>=0.27.0
Requires-Dist: jinja2<4,>=3.1.2
Requires-Dist: json-repair<0.35,>=0.34.0
Requires-Dist: jsonschema>=4.25.1
Requires-Dist: lark<2,>=1.2.2
Requires-Dist: libcst<2,>=1.8.2
Requires-Dist: litellm>=1.80.10
Requires-Dist: onepassword-sdk==0.3.0
Requires-Dist: openai>=1.68.2
Requires-Dist: orjson<4,>=3.9.10
Requires-Dist: pandas<3,>=2.3.1
Requires-Dist: pdfplumber<0.12,>=0.11.0
Requires-Dist: pillow>=10.2.0
Requires-Dist: playwright==1.46.0; python_version >= '3.11' and python_version < '3.12'
Requires-Dist: playwright>1.46.0; python_version >= '3.12' and python_version < '3.14'
Requires-Dist: posthog<4,>=3.7.0
Requires-Dist: psutil>=7.0.0
Requires-Dist: psycopg[binary,pool]<3.3.0,>=3.2.2; python_version >= '3.13' and python_version < '3.14'
Requires-Dist: psycopg[binary,pool]==3.1.18; python_version >= '3.11' and python_version < '3.13'
Requires-Dist: pydantic-settings<3,>=2.1.0
Requires-Dist: pydantic<3,>=2.5.2
Requires-Dist: pyotp<3,>=2.9.0
Requires-Dist: pypdf<6,>=5.1.0
Requires-Dist: python-calamine>=0.6.1
Requires-Dist: python-dotenv<2,>=1.0.0
Requires-Dist: python-jose[cryptography]<4,>=3.4.0
Requires-Dist: python-multipart<0.0.19,>=0.0.18
Requires-Dist: requests-toolbelt<2,>=1.0.0
Requires-Dist: rich[jupyter]<14,>=13.7.0
Requires-Dist: sqlalchemy[mypy]<3,>=2.0.29
Requires-Dist: starlette-context<0.4,>=0.3.6
Requires-Dist: structlog<24,>=23.2.0
Requires-Dist: tiktoken>=0.9.0
Requires-Dist: tldextract<6,>=5.1.2
Requires-Dist: toml<0.11,>=0.10.2
Requires-Dist: typer>=0.16.0
Requires-Dist: types-boto3[full]<2,>=1.38.31
Requires-Dist: types-toml<0.11,>=0.10.8.7
Requires-Dist: uvicorn[standard]<0.25,>=0.24.0.post1
Requires-Dist: websockets~=12.0
